trytond/modules/party_fieldaddon/README.rst
trytond/modules/party_fieldaddon/__init__.py
trytond/modules/party_fieldaddon/address.py
trytond/modules/party_fieldaddon/address.xml
trytond/modules/party_fieldaddon/configuration.py
trytond/modules/party_fieldaddon/configuration.xml
trytond/modules/party_fieldaddon/party.py
trytond/modules/party_fieldaddon/party.xml
trytond/modules/party_fieldaddon/tryton.cfg
trytond/modules/party_fieldaddon/versiondep.txt
trytond/modules/party_fieldaddon/locale/de.po
trytond/modules/party_fieldaddon/locale/en.po
trytond/modules/party_fieldaddon/tests/__init__.py
trytond/modules/party_fieldaddon/tests/test_party.py
trytond/modules/party_fieldaddon/view/address_format_form.xml
trytond/modules/party_fieldaddon/view/address_preview_form.xml
trytond/modules/party_fieldaddon/view/configuration_form.xml
trytond/modules/party_fieldaddon/view/party_form.xml
trytond/modules/party_fieldaddon/view/party_tree.xml
mds_party_fieldaddon-7.0.14.dist-info/METADATA
mds_party_fieldaddon-7.0.14.dist-info/WHEEL
mds_party_fieldaddon-7.0.14.dist-info/entry_points.txt
mds_party_fieldaddon-7.0.14.dist-info/top_level.txt
mds_party_fieldaddon-7.0.14.dist-info/RECORD
